{
    "introduction": "华南地区，简称华南，是中国七大地理分区之一，位于中国南部。包括广东省、广西壮族自治区、海南省、香港特别行政区、澳门特别行政区。民国时代， ",
    "attributes": {
        "中文名": "华南地区",
        "外文名": "Southern China",
        "所属地区": "中华人民共和国",
        "地理位置": "中国南部",
        "面积": "452900 km²",
        "下辖地区": "广东、广西、海南、香港、澳门",
        "气候条件": "亚热带季风气候、热带季风气候",
        "人口数量": "1.69 亿(2012年常住人口)",
        "著名景点": "桂林山水、天涯海角、大三巴牌坊、珠玑古巷、百里柳江、广州塔",
        "机场": "广州白云国际机场、香港国际机场、深圳宝安国际机场、南宁吴圩国际机场、澳门国际机场、海口美兰国际机场、桂林两江国际机场",
        "火车站": "广州南站、深圳北站、南宁东站、桂林北站、海口东站等",
        "车牌代码": "粤、桂、琼、港、澳",
        "img": "https://bkimg.cdn.bcebos.com/pic/8644ebf81a4c510f497f78a36e59252dd52aa5d4?x-bce-process=image/resize,m_lfit,w_536,limit_1/format,f_jpg"
    },
    "relation": {
        "person": {},
        "location": {},
        "date": {},
        "organization": {},
        "event": {}
    },
    "timeLine": [],
    "type": "LOCATION"
}