{
    "introduction": "岳北农工会旧址位于衡阳市衡山县白果镇，岳北农工会为湖南最早的农民革命组织、全国第一个工农联合的革命组织。中共湘区委员会发动和领导了20世纪20年代的湖南农民运动。1923年4月，中共湘区委派遣水口山工人中的共产党员刘东轩、谢怀德回到家乡衡山岳北开展农民运动，并于同年9月建立岳北农工会。这是湖南建立秘密农协的开始，成为湖南农民运动的先声。1927年初毛泽东在衡山考察农民运动时，特别高度评价了衡山农民斗争的创造精神。",
    "attributes": {
        "中文名": "岳北农工会",
        "外文名": "YueBei a&m will",
        "重要意义": "中国第一个工农联合革命组织",
        "建立时间": "1923年9月",
        "人数": "40000人以上",
        "旧址": "衡阳市衡山县白果镇"
    },
    "relation": {},
    "timeLine": [
        [
            "1921年",
            "未知",
            "1921年，党的一大召开后，全国建立了三处最早的农民革命组织，各有特色，浙江萧山衙前农民协会，成立时间最早；广东海丰农民协会，声势、规模最大；衡阳衡山岳北农工会，则是工农联合在全国的第一个",
            "岳北农工会:全国建立了三处最早的农民革命组织"
        ],
        [
            "1922年",
            "岳北",
            "1922年岳北人民受安源煤矿、水口山铅锌矿工人举行声势浩大的罢工运动教育和启发，看到了翻身得解放的光明前景",
            "岳北农工会:看到了翻身得解放的光明前景"
        ],
        [
            "1923年4月",
            "岳北",
            "1923年4月，湘区委员会选派水口山铅锌矿优秀干部刘东轩、谢怀德带着革命的火种，回家乡岳北发动组织农民运动",
            "岳北农工会:回家乡岳北发动组织农民运动"
        ],
        [
            "1923年9月16日",
            "衡阳、衡山、岳北",
            "经过积极筹备，1923年9月16日，岳北农工会在刘捷三公祠召开数千人参加的成立大会，宣布全省最早的农民阶级革命组织—衡阳衡山岳北农工会正式成立",
            "岳北农工会:宣布全省最早的农民阶级革命组织—衡阳衡山岳北农工会正式成立"
        ],
        [
            "1925年6月",
            "衡山",
            "1925年6月，中共湘南特委（中共湘南地方执行委员会）选派进步教师刘爱农等，回家乡衡山建立了党组织",
            "岳北农工会:回家乡衡山建立了党组织"
        ],
        [
            "1926年",
            "白果",
            "1926年冬至那天，白果刘氏宗祠摆了数十桌酒席开堂祭祖，女界联合会负责人朱隶堂率领30多名剪一色短发、手拿梭标的妇女，涌入祠堂一屁股坐下便吃酒",
            "岳北农工会:涌入祠堂一屁股坐下便吃酒"
        ],
        [
            "1926年12月",
            "岳北",
            "岳北农民运动在全省享有盛誉，1926年12月，全省第一次工农代表大会召开，岳北农会干部彭桂峰出席大会，并在会上介绍岳北农运发展情况",
            "岳北农工会:并在会上介绍岳北农运发展情况"
        ],
        [
            "1927年",
            "宋桥、衡山县城、湘乡、白果、福田铺",
            "为了驳斥党内外对农民运动的攻击和责难，毛泽东同志于1927年1月15日至24日来衡山，由湘乡→白果→福田铺→世上冲(宋桥)→衡山县城考察了衡山农民运动",
            "岳北农工会:由湘乡→白果→福田铺→世上冲(宋桥)→衡山县城考察了衡山农民运动"
        ],
        [
            "1927年",
            "中国、江西安源",
            "1927年，蒋介石发动了“四一二”反革命政变，岳北部分工农武装力量转赴江西安源，编入工农革命军第一军第一师第二团，参加了毛泽东同志领导的秋收起义，并跟随毛泽东奔赴井岗山，开辟以农村包围城市，武装夺取政权，解放全中国的道路",
            "岳北农工会:并跟随毛泽东奔赴井岗山"
        ]
    ],
    "type": "ORGANIZATION"
}