{
    "introduction": "陕甘宁，拼音是shǎn gān níng，汉语词语，意思是陕西、甘肃、宁夏 的合称。",
    "attributes": {
        "中文名": "陕甘宁",
        "拼音": "shǎn gān níng",
        "注音": "ㄕㄢˇ ㄍㄢ ㄋㄧㄥˊ",
        "释义": "陕西 、 甘肃 、 宁夏 的合称"
    },
    "relation": {
        "person": {},
        "location": {},
        "date": {},
        "organization": {},
        "event": {}
    },
    "timeLine": [
        [
            "一九四一年三月",
            "延安、绥德、陕甘宁",
            "” 左齐 《南泥湾屯垦·安营扎寨》：“一九四一年三月，我们肩负着保卫党中央和 陕甘宁边区 重任的三五九旅部队，从 绥德 向 延安 的 南泥湾 出发了",
            "陕甘宁:从 绥德 向 延安 的 南泥湾 出发了",
            "109.50118366576285,36.656089661066176"
        ]
    ],
    "type": "ORGANIZATION"
}