{
    "introduction": "建屏县于1940年8月13日在获鹿县（今鹿泉区）的牛山村正式建立。其县名是为纪念晋察冀四分区司令员周建屏而命名的，俗称“东建屏”。",
    "attributes": {
        "中文名": "建屏县",
        "外文名": "Jian PingCounty",
        "别名": "东建屏",
        "行政区类别": "县",
        "所属地区": "石家庄市"
    },
    "relation": {
        "person": {},
        "location": {},
        "date": {},
        "organization": {},
        "event": {}
    },
    "timeLine": [
        [
            "1940年8月13日",
            "牛山村、获鹿县、建屏县、获鹿",
            "建屏县于1940年8月13日在获鹿县（今鹿泉区）的牛山村正式建立",
            "建屏:建屏县于1940年8月13日在获鹿县（今鹿泉区）的牛山村正式建立",
            "114.52008311444797,30.31862981048972"
        ],
        [
            "1945年10月",
            "建屏县、平山县城、平山县",
            "1945年10月，抗战胜利后，取消建屏县（东建屏），原平山县城东区域仍归属平山县",
            "建屏:原平山县城东区域仍归属平山县",
            "0,0"
        ],
        [
            "1949年1月",
            "北岳、察哈尔省、建屏",
            "另在1949年1月察哈尔省成立后，将原北岳区四专署改为建屏专署，北岳四地委改为中共察哈尔省建屏地委",
            "建屏:北岳四地委改为中共察哈尔省建屏地委",
            "113.95251418528402,23.055311438376187"
        ],
        [
            "1940年8月",
            "建屏县、鹿泉、牛山",
            "1940年8月，经北岳区党委和晋察冀边区政府的批准，在鹿泉牛山成立建屏县",
            "建屏:在鹿泉牛山成立建屏县",
            "0,0"
        ],
        [
            "1945年10月",
            "洪子店、岗南、温塘、建屏县、平山、平山县",
            "1945年10月，县域重新调整，以平山县温塘、岗南西部的自然山岭为界，整个西部的山区、半山区，重组建屏县，县政府所在地为洪子店",
            "建屏:整个西部的山区、半山区",
            "114.02099346632875,38.238932164582245"
        ],
        [
            "1947-1949年",
            "建屏县、小觉、北冶",
            "1947-1949年间，晋察冀解放区在建屏县的军工企业就有15家之多，主要集中在建屏县北冶、小觉一带",
            "建屏:主要集中在建屏县北冶、小觉一带",
            "0,0"
        ],
        [
            "90周年",
            "未知",
            "周建屏烈士的英名不会因为地名的变更而消逝，在纪念建党90周年的日子里，我们再来重温他生前说过的一段话，简直可以作为共产党人的豪迈宣言：“我当过光绪、宣统、洪宪三个皇帝的臣民，也参加了推翻他们的斗争",
            "建屏:也参加了推翻他们的斗争",
            "0,0"
        ],
        [
            "1939年",
            "小觉镇、建屏县、平山、获鹿、平山县、井陉",
            "为纪念这位南征北战、屡建奇功的八路军优秀将领，1939年，在平山县小觉镇东山坡上修建了周建屏烈士陵园，并先从平山、井陉、获鹿三县分别划出部分地区，成立建屏县",
            "建屏:成立建屏县",
            "113.7272590628765,38.401168975258635"
        ]
    ],
    "type": "LOCATION"
}