{
    "introduction": "1927年7月中旬，中共中央决定在江西南昌举行起义，并成立了以周恩来为书记的前敌委员会。",
    "attributes": {
        "中文名": "中共中央前敌委员会",
        "img": ""
    },
    "relation": {
        "person": {},
        "location": {},
        "date": {
            "成立时间": "1927年7月"
        },
        "organization": {},
        "event": {}
    },
    "timeLine": [
        [
            "1927年7月27日",
            "未知",
            "1927年7月27日，中共中央指定周恩来、李立三、恽代英、彭湃成前敌委员会,周恩来任书记,组织领导南昌起义",
            "中共中央前敌委员会:组织领导南昌起义",
            "0,0"
        ]
    ],
    "type": "ORGANIZATION"
}