{
    "introduction": "《间谍同盟》是由美国派拉蒙影业公司出品的动作爱情片，由罗伯特·泽米吉斯执导，布拉德·皮特、玛丽昂·歌迪亚领衔主演。《间谍同盟》以二战为故事背景，讲述了英国特工麦克斯与法国间谍玛丽安在刺杀德国大使任务中坠入爱河，从而上演一段荡气回肠的爱情故事。该片于2016年11月23日在美国上映，于2016年11月30日在中国上映。>>>《间谍同盟》是由美国派拉蒙影业公司出品的动作爱情片，由罗伯特·泽米吉斯执导，布拉德·皮特、玛丽昂·歌迪亚领衔主演。《间谍同盟》以二战为故事背景，讲述了英国特工麦克斯与法国间谍玛丽安在刺杀德国大使任务中坠入爱河，从而上演一段荡气回肠的爱情故事。该片于2016年11月23日在美国上映，于2016年11月30日在中国上映 。",
    "attributes": {
        "中文名": "间谍同盟",
        "外文名": "Allied",
        "别名": "鹣鲽同盟（台湾）、五秒钟的沉默、联盟",
        "出品时间": "2016年",
        "出品公司": "派拉蒙影业公司（美国）、华桦传媒（中国）",
        "制片地区": "美国",
        "拍摄地点": "摩洛哥、法国、英国",
        "导演": "罗伯特·泽米吉斯",
        "编剧": "斯蒂文·奈特",
        "制片人": "格拉汉姆·金",
        "类型": "爱情、谍战、剧情、动作",
        "主演": "布拉德·皮特、玛丽昂·歌迪亚、杰瑞德·哈里斯、西蒙·迈克伯尼、丽兹·卡潘、丹尼尔·贝茨",
        "片长": "121分钟",
        "上映时间": "2016年11月23日（美国）、2016年11月30日（中国）",
        "对白语言": "英语",
        "色彩": "彩色",
        "img": ""
    },
    "relation": {
        "person": {},
        "location": {},
        "date": {},
        "organization": {},
        "event": {}
    },
    "timeLine": [],
    "type": "ORGANIZATION"
}